data_model_orm/__init__.py
data_model_orm/base.py
datamodel_orm-1.0.0.dist-info/METADATA
datamodel_orm-1.0.0.dist-info/WHEEL
datamodel_orm-1.0.0.dist-info/top_level.txt
datamodel_orm-1.0.0.dist-info/RECORD
