Metadata-Version: 2.1
Name: datamodel_orm
Version: 1.0.0
Summary: A fast and efficient way to interact with databases using pydantic models
Author-email: Tobias Ahlers <93325697+TobiasAhlers@users.noreply.github.com>
Project-URL: Homepage, https://github.com/TobiasAhlers/DataModel-ORM
Project-URL: Issues, https://github.com/TobiasAhlers/DataModel-ORM/issues
Classifier: Programming Language :: Python :: 3
Classifier: Operating System :: OS Independent
Requires-Python: >=3.11
Requires-Dist: sqlmodel
